README.md
setup.py
lmz/__init__.py
lmz/__version__.py
lmz.egg-info/PKG-INFO
lmz.egg-info/SOURCES.txt
lmz.egg-info/dependency_links.txt
lmz.egg-info/top_level.txt