Metadata-Version: 1.2
Name: lmz
Version: 0.1.12
Summary: return lists
Home-page: https://github.com/smautner/listmapzip
Author: Stefan Mautner
Author-email: myl4stn4m3stef@gmail.com
License: GPLv3
Platform: UNKNOWN
Requires-Python: >=3.8
